lapack4abaqus/__init__.py
lapack4abaqus/_version.py
lapack4abaqus/gen_lapack.py
lapack4abaqus-1.0.8.dist-info/LICENSE
lapack4abaqus-1.0.8.dist-info/METADATA
lapack4abaqus-1.0.8.dist-info/WHEEL
lapack4abaqus-1.0.8.dist-info/top_level.txt
lapack4abaqus-1.0.8.dist-info/RECORD
