Metadata-Version: 2.1
Name: lapack4abaqus
Version: 1.0.8
Summary: Create lapack.f for Abaqus to include.
Author-email: HUANG Lihao <huang-lihao@outlook.com>
Project-URL: Homepage, https://github.com/huang-lihao/lapack4abaqus
Project-URL: Bug Tracker, https://github.com/huang-lihao/lapack4abaqus/issues
Classifier: Programming Language :: Python :: 3
Classifier: License :: OSI Approved :: MIT License
Classifier: Operating System :: OS Independent
Requires-Python: >=3.7
License-File: LICENSE
